mmanalyser/__init__.py
mmanalyser/audio_analyser.py
mmanalyser/config.py
mmanalyser/emotion_analyser.py
mmanalyser/expression_analyser.py
mmanalyser/fluctuation_detector.py
mmanalyser/heart_rate_analyser.py
mmanalyser/data/gbdt
mmanalyser/data/gbdtMEANS
mmanalyser/data/suffix.txt
mmanalyser/utils/nlu_tools.py
mmanalyser/utils/number_to_chinese.py
mmanalyser/utils/suffix_remover.py
mmanalyser/utils/vad.py
mmanalyser/utils/wer.py
mmanalyser-0.6.0.dist-info/LICENSE
mmanalyser-0.6.0.dist-info/METADATA
mmanalyser-0.6.0.dist-info/WHEEL
mmanalyser-0.6.0.dist-info/top_level.txt
mmanalyser-0.6.0.dist-info/RECORD
