Metadata-Version: 2.1
Name: mmanalyser
Version: 0.6.0
Summary: a tool for multimedia
Home-page: UNKNOWN
Author: xujc
Author-email: 
License: UNKNOWN
Platform: UNKNOWN
Classifier: Programming Language :: Python :: 3
Classifier: License :: OSI Approved :: MIT License
Classifier: Operating System :: OS Independent
Requires-Python: >=3.5
Requires-Dist: pydub (==0.23.1)
Requires-Dist: pandas (==0.25.3)
Requires-Dist: etools (==0.0.10)
Requires-Dist: pyAudioAnalysis (==0.3.0)
Requires-Dist: webrtcvad (==2.0.10)
Requires-Dist: python-Levenshtein (==0.12.0)
Requires-Dist: pypinyin (==0.37.0)
